{
    "manifestVersion": 1,
    "id": "theme-clear-dawn",
    "version": "0.2.1",
    "name": "Clear Dawn",
    "publisher": "ivanhernandez",
    "description": "A desaturated, high contrast, light theme",
    "license": "SEE LICENSE IN License.md",
    "engines": {
        "vscode": "^1.13.0"
    },
    "targets": [{
        "id": "Microsoft.VisualStudio.Services"
    }],
    "icons": {
        "default": "logo.png"
    },
    "categories": [
        "Themes"
    ],
    "branding": {
        "color": "rgb(254, 246, 240)",
        "theme": "light"
    },
    "content": {
        "details": {
            "path": "readme.md"
        },
        "license": {
            "path": "LICENSE.txt"
        }
    },
    "repository": {
        "type": "git",
        "uri": "https://github.com/ivanhernandez/theme-clear-dawn"
    }
}